Metadata-Version: 2.1
Name: odoo-addon-l10n_ro_account_edi_ubl
Version: 16.0.1.89.0
Summary: Romania - eFactura - Account EDI UBL
Home-page: https://github.com/OCA/l10n-romania
Author: Terrabit,NextERP Romania,Odoo Community Association (OCA)
Author-email: support@odoo-community.org
License: AGPL-3
Classifier: Programming Language :: Python
Classifier: Framework :: Odoo
Classifier: Framework :: Odoo :: 16.0
Classifier: License :: OSI Approved :: GNU Affero General Public License v3
Classifier: Development Status :: 6 - Mature
Requires-Python: >=3.10
Requires-Dist: odoo-addon-l10n-ro-account-anaf-sync<16.1dev,>=16.0dev
Requires-Dist: odoo-addon-l10n-ro-partner-create-by-vat<16.1dev,>=16.0dev
Requires-Dist: odoo<16.1dev,>=16.0a
